{
  "following": "Following",
  "followingDesc": "Follow original series to get notified anytime a new episode or season is released. You can always update your preferences here.",
  "followingEmpty": "You’re not following any series at the moment. Select a few to follow and you’ll receive notifications anytime a new episode or season is released.",
  "findMoreOriginalPrograms": "Find more Gaia original programs",
  "season": "Season",
  "seasons": "Seasons",
  "episode": "Episode",
  "episodes": "Episodes",
  "followingSeries": "Following Series",
  "followSeries": "Follow Series",
  "member": "Member"
}
