{
  "watchNow" : "Ver ahora",
  "watchPreview" : "Ver vista previa",
  "video" : "Video",
  "series" : "Series",
  "episode" : "Episodio",
  "watchNextEpisode" : "Ver el próximo episodio",
  "watchTrailer" : "Ver el tráiler",
  "resume" : "Continuar",
  "signup" : "Suscríbete y empieza ya",
  "upgradeToWatch" : "Cambia al Plan Eventos en Streaming",
  "notAvailableInRegion" : "No disponible en la región",
  "discoverGaia" : "Descubre lo que Gaia tiene para ofrecer gratis.",
  "continueWatching" : "Seguir viendo"
}
